{"comments": [{"author": "Kamil", "date": "2010-04-15 08:23:48", "content": "I think I stayed in that hostel before...and it was bloody cold!!"}, {"author": "Lo\u00efc", "date": "2010-04-15 09:26:12", "content": "I stayed in that hostel too! 5 years ago, in summer.<br/>The owner, a very old man at that time, used to play a loud (kind of military) song early in the morning to wake up people :)<br/>Have fun on the downhill slopes! After that trip, you will be ready for the Tour de France race in July."}]}